nmdc_notebook_tools/__init__.py
nmdc_notebook_tools/biosample_search.py
nmdc_notebook_tools/calibration_search.py
nmdc_notebook_tools/chemical_entity_search.py
nmdc_notebook_tools/collecting_biosamples_from_site_search.py
nmdc_notebook_tools/collection_helpers.py
nmdc_notebook_tools/collection_search.py
nmdc_notebook_tools/configuration_search.py
nmdc_notebook_tools/data_generation_search.py
nmdc_notebook_tools/data_object_search.py
nmdc_notebook_tools/data_processing.py
nmdc_notebook_tools/example_usage.py
nmdc_notebook_tools/field_research_site_search.py
nmdc_notebook_tools/functional_annotation_agg_search.py
nmdc_notebook_tools/functional_search.py
nmdc_notebook_tools/instrument_search.py
nmdc_notebook_tools/lat_long_filters.py
nmdc_notebook_tools/manifest_search.py
nmdc_notebook_tools/material_processing_search.py
nmdc_notebook_tools/nmdc_search.py
nmdc_notebook_tools/processed_sample_search.py
nmdc_notebook_tools/protocol_execution_search.py
nmdc_notebook_tools/storage_process_search.py
nmdc_notebook_tools/study_search.py
nmdc_notebook_tools/utils.py
nmdc_notebook_tools/visualize.py
nmdc_notebook_tools/workflow_execution_search.py
nmdc_notebook_tools/test/__init__.py
nmdc_notebook_tools/test/test_biosample.py
nmdc_notebook_tools/test/test_collection.py
nmdc_notebook_tools/test/test_func_ann_agg.py
nmdc_notebook_tools/test/test_study.py
nmdc_notebook_tools-0.2.3.dist-info/METADATA
nmdc_notebook_tools-0.2.3.dist-info/WHEEL
nmdc_notebook_tools-0.2.3.dist-info/top_level.txt
nmdc_notebook_tools-0.2.3.dist-info/RECORD
