Metadata-Version: 2.2
Name: nmdc_notebook_tools
Version: 0.2.3
Summary: A Python library for general research functions using NMDC APIs
Author-email: Olivia Hess <olivia.hess@pnnl.gov>
License: MIT
Classifier: Programming Language :: Python :: 3
Classifier: Operating System :: OS Independent
Requires-Python: >=3.10
Requires-Dist: pandas>=2.2.3
Requires-Dist: requests>=2.32.3
Requires-Dist: matplotlib==3.10.0
